un_fstring.py
un_fstring-0.1.3.dist-info/LICENSE
un_fstring-0.1.3.dist-info/METADATA
un_fstring-0.1.3.dist-info/WHEEL
un_fstring-0.1.3.dist-info/entry_points.txt
un_fstring-0.1.3.dist-info/top_level.txt
un_fstring-0.1.3.dist-info/RECORD
