Metadata-Version: 2.1
Name: un-fstring
Version: 0.1.3
Summary: A tool to convert f-strings to .format() calls.
Home-page: UNKNOWN
Author: Josh Karpel
Author-email: josh.karpel@gmail.com
License: MIT
Platform: UNKNOWN
Classifier: Development Status :: 3 - Alpha
Classifier: Intended Audience :: Developers
Classifier: License :: OSI Approved :: MIT License
Classifier: Operating System :: OS Independent
Classifier: Programming Language :: Python :: 3
Classifier: Programming Language :: Python :: 3 :: Only
Classifier: Programming Language :: Python :: 3.6
Classifier: Programming Language :: Python :: 3.7
Classifier: Programming Language :: Python :: 3.8
Requires-Python: >=3.6
Requires-Dist: astroid
Requires-Dist: tokenize-rt
Provides-Extra: tests
Requires-Dist: mypy ; extra == 'tests'
Requires-Dist: pytest (>=6) ; extra == 'tests'
